{
"tfjetxptg2ittfpwx6zq3utf":"29once",
"idpy6zlseciscvfotecjkcjz":["abyssalcats","Once and Future Catlady"],
"zo7vntepflyse4asmwfts2vf":["alistartdraws","guy once more named yaoi"],
"7vhtgkvrazweled2inyevbfx":["amarylliss","sarah. amaryllis. the user once known as cake."],
"vzvm3w2eh7jmrv6jz2ztki3z":["aswaggerprince","once a swaggerprince always a swaggerprince"],
"piieevimavccp34jgezdqkoc":["bbsmaitake","Pink_Once "],
"lfl3kliaqoovn7vvgngesdcc":["bey-once","💭."],
"wa4y44c2tezjeetmhcbyluzx":["brownponcho","Brown P Oncho"],
"yyxcnf5of6hvno3awguheawt":["causticsodapop","UseOnceAndDestroy"],
"4dpiv27fimk6o5pp7nn72ygd":["challyndin","Once A Rebel "],
"tw6teezsecxil3cfbwsnbpco":["chavmd","Pup Oncore ❤️‍🔥"],
"dpj77rxntzbiqolkduzvjlah":["cloakred","Once Red"],
"6kvntlkkkyvlj5mkigp5dzxj":["cyncordura","Dra. Oncilla "],
"6givpc444hvehfc365ejfp3t":["danteku","Danny Danteku, once DTerryM 🎮"],
"qwra4kvwnn272uxtgye7ig4m":["deandrawrites","DeAndra | add ALL THE NOISE AT ONCE on GR!"],
"qvkdohnoophbjdnvj4gnosaa":["don53713","Making Don Great Again 🌻🇺🇦 Once Upon an Ops NCO"],
"gmnp7o25ynk5y54er4hiv75p":["drivelikejesu","The Once and Future Al Pachinko"],
"mmsxg3bh6qm3gqxehulkicp4":["emf-v","Crazy? I was crazy once."],
"s46rrmesdvoxzz3vade2znuq":["etaopod.com","Everybody's Talking At Once"],
"kskr4wt5cibzapm7gsvswnoe":["ettyus","As Your god is Failing Once Again "],
"isuhl7p4rs3oerh32qyb5n2j":["facestabberxoxo","Blaséoncake"],
"xabs6retbmkkmadgsniqtmhq":["feelers","Once more with feelers"],
"bsdlxd244q52eixgwhgghdmy":["flowersforjoy","✿ Princess Joy ✿ #OnceUponATimeVNJam ♟️"],
"42ypyxlt7aylz6xs3bqaj6px":["futureeric","Once and For All"],
"gzxzoft4jq2ntfwlf4yic2z4":["gentleman-once","Gentleman Once"],
"mn7n7gms6qms42ylyjiptgdt":["heysawbones","Once in a Lifetime"],
"k5beqsjj55c7edqedhjovvs6":["j4ck","j4ck is onchain"],
"27ebz6qtauncughi5uf7prwu":["kitsunesque","jack @ the bra tree once more"],
"kmcvnbwcb23vr4bnbnnzgozz":["knockonceforyes","Knock Once For Yes"],
"c4bzzdro3lao2cp34ew2ngds":["lavelled","once in a lunchtime "],
"rbtw6youtttfgabmofuhcjtd":["m0onchae.woke.cat","babi⁷"],
"2i6nxzgkncust36375mw6rco":["maelys","Maeys exiled once again"],
"nsgwyndkbhot2hdwu4i5cb3n":["me9","Onchari"],
"clkevocidkrxpiwdecmd6hot":["michellepraiz","Michelle Praiz once again..."],
"zirbwvqj33tcist4cj7xxeil":["miraculous","MIHDND in: Once in a Bluesky"],
"sfn57onasydp6c4rhphuaxz6":["mo0onchild","Moonchild"],
"hqzpigp36kisalfbxkdyb663":["myheart","Once upon a time"],
"l3mf66rtww4wlfoxaggsmdyf":["notevenonce","Not Even Once"],
"l2rzndmladedkenw4viomyd4":["officialgoogirl","It's liz once again"],
"aqioknge3hnd3ml5w6xpo2an":["onceatrophic","Andrew Wasserman "],
"jazqvj7wljnzu5qbl6jvdesk":["oncelivingsol","Сол"],
"jipg6bskfzgbmhqmi25wuooa":["oncecaution","⚠️Spooky DoeBoy 🔜MFF ⚠️ "],
"lahxosdo3s5g6nuepizzn5xk":["onceuponageek","Irredeemable Shag"],
"mnx7clmnzffpansan7vtmgzu":["onclegabo","Gabora"],
"nxkhxayyw4xftuyitswjte7j":["onclephil","Oncle Phil"],
"rsuximy6xivze6lmmvd5epja":["onceapanda","Pandamonium "],
"svi2r4362gscw35p3h7y73kd":["onceuponawasteland.com","Once Upon a Wasteland"],
"tdbw4msqen5amu6r2amde6b4":["onceincycling","O.N.C.E. Upon a Time in Cycling"],
"tfbpayhljksvgrgqiqrjmelo":["oncloude","Cloudy 🌥️ (estrogen angel)"],
"u45mbqtshovp6vo5xbvb3xm5":["onceuponatime","✍🏻"],
"v6zsjsj7rqkdlxaaijx3igrx":["onceinalifetime","Arianna"],
"kdkfy5qlrlpjvcdtgmez6ywt":["oncescuradu","Radu Oncescu"],
"xo2zfwu3bxvywmqrkvzrud5k":["onchain","onchain"],
"4p6dkkggrzsedoqpe7mm3fnz":["onchaintv","OnChainTV"],
"qmic4gluwtets5anj4a66qq2":["oncewasmel","Mel"],
"r3iw7pmpjkc5a4xxxlhdsgth":["once","bea"],
"3tukc3btpfqekekuflzggjzv":["oncesabrina","bella 💌"],
"va726rn4xmifbsnzcoaecf6m":["onceandforall","약국"],
"voi5uhoxfvqjqe5kk2zit6en":"oncemattew",
"c7vdabf7l2ovvqpc2kvc23ce":["onc11","ONC11"],
"rmnmziomdteu5cl3glyah5vu":"onchainbook",
"ugtysuayxl4kxjq5mx4rcsef":["oncunesil","Öncü Nesil Derneği "],
"iyazuwwptfi35btczhy57t7g":["onceupona94","onceupona94"],
"5cwc6mrpvoyntelwtxkuscs2":["onemoreday","All At Once "],
"43s56ef2v4aziscuxtvml4bl":["oncewas","Once"],
"6lmhbpix2sea6dbx422irpom":["oncallgm","Thurston Hillman"],
"hrowbc75q3mnxvqnk7ldopyo":["oncalupe","OncaLupe"],
"zgghedqc3popd7k4o73mb5am":["oncomingtraffic","Traffic/Sparkz"],
"sa5s5g3nnantrjdh6bfc5vla":["onceinawildzoo","Once in a Wild"],
"4bxzxoggz6tnb6rf2g4vpkvj":["onceuponatom","Once upon a Tom in Hollywood"],
"jgpw5xgjnjw6suzpcale6wqv":"oncreenkodiak",
"nyk54qqbtfiptvnskbkegnc5":["onchanonion","ネッコ"],
"e3xm5eunxukfdzv36xmwd7wv":["onceler","The Onceler"],
"jgsnxhjrrok6tsup7mwlfjes":["onceuponapuppet","Once Upon a Puppet"],
"owjwuvnxnpo7e5wd6llezfbt":["onceuponatown","Once Upon a Town"],
"opwcnimijui67bf6ymrwoqir":"oncourse",
"6ezwnxjfcdlx4b7hplq2rozq":"onca",
"dn7j4oewjjg3ei2c7zr2qen2":["onclefernand","Oncle Fernand"],
"oqb7lc6twabzftjlrjno4nll":["oncoplastics","Alex Brown"],
"z24ophpyotponzdcvq5p652d":"oncuuner",
"7etvdmiqj65alzeg4ymn2o4q":["oncapintada","jaguar!! 🐆"],
"6erx3ns5u6pzw3g2uypb5wol":["onceandfuturekeith","Keith Mitchell"],
"moqklqbjefgrwiepvdjp65ke":["oncebitrevelee","ren 🌻"],
"mhf3lad53klqpihvnd2mrwiy":"onceuponatime78",
"sj7z7gnm7uml4luo4ydqsaur":["oncogene","Oncogene"],
"2xwnwhpaatr33etdlwwsorva":"oncegruntled",
"domtekhujc7s5w24uuvua2gm":"oncebot",
"s65rzgu42gjecierihv3beh7":"oncyberai",
"skepc4di5fpgm24w5gdcetww":["onchange","onchange"],
"qz6637tmhmoodjp2xmbj5ws7":["oncruu","inianovrianti"],
"kqe73enupry7g6ncm5t7myki":["onchao","Roadhog's wife"],
"ebujqjax53hjhklkyn22dsys":["onceuponaweeny","WEENY"],
"u5gnwf6snmwl6tugmdd7z7ba":"oncomouse",
"dlo7i42vc2yjg3epxej2d4gw":["onceamoose","Chris Chappel"],
"lkslmlkn6t6vitm3y4uw223h":["oncinemaquotes","Lon Cinema's On Cinema Quotes"],
"6hszgldubifxqkmymrxpox4h":"oncertainty",
"f6bt6huyzhp3j4h2kexkbhvp":["onchyophoran","basura"],
"u272qwnek3xwj7jyj44sebta":["onchaaaa","온차"],
"kr6fl5lh5qxvdbpvf2ybphaq":["onceuponafine","Abigail Fine"],
"sjlxv3aawnbd5iknuoc4bbc4":["onco99","Onco99"],
"b2sm3s7lyvs2o7koww3cvwbu":["onceuponatimmy","Tim"],
"kbkcxirkr6g4v7tbdpl4male":"onceandfuture",
"3ezfdemz3ssyxjsg47apaxib":["onceinawhile62","silent beta"],
"gonqqc5yixbi56sjraapvoqq":["onceuponvienna","David - Once upon a time in Vienna "],
"lwjhzshcm3yf22pm4rqiqwwj":["oncequirkyjoyce","JoyceE"],
"uqz6rptwe3tedymth5pgg5d4":["oncewassven","Oncewassven"],
"lnybttlkrqdwe4kif6y45e2r":["onceuponakinga","Kinga"],
"dyqjyuovyeum5atotgiz6n3f":"oncoutinho",
"jkv56q7jj6g3wgteovphmpmg":["oncedarkness","Erin"],
"ndaqf6ivpkopbaokh7re7vjm":["onceayse","Ayşe"],
"ni444hbskx6teybsynzcqcgi":["onceuponaquest","Once Upon A Quest"],
"3o2k4ahlrrugfamgctuyuzhj":"once-wayward",
"zemgywujqclorkgvuuthgp7z":["onceagain","Nancy Taylor  "],
"zem3bjzbnu5qtbvv7i4pqgud":["oncmingstorm","mya of siobhan "],
"rgoxklrk3v6pahsrlmex45qd":["onchainmusic","OnChain Music"],
"e4qiihmy5cx7nfrhkgmy6rwe":["oncloudadam","☁️Adam or Cloud☁️"],
"uxb6oqoqjwjscnl7xh7cplhw":"oncoursek12",
"oo2rtctquv3reqtzkvsmrxmi":["oncetagram0922","나숭이사랑"],
"gii5bfg4g5c5lzfzwwt6ezrq":["onceagainz","DemonicTrebuchet "],
"awlra4gycjj66sw5y3abzsfb":["onceabluemoon","OnceABlueMoon"],
"rc6xopohn5nc4hfy3l6kznfa":["onceuponadonna","Donna McKay"],
"5ub4kfb6yhr6hzzogviwpobg":"oncaix",
"qu2sjfxlvdz7njxh3kswuwe6":["oncewasarnold","Once_Was_Arnold"],
"lqcsxuuasxj2sqvqkcyou5xj":["onceeponatime","Claire"],
"iyncsqhra6exyqwedhjpxiy4":"onceler239",
"flkcypypwobkknzzmspqnn2e":["oncelers","Vince 🐌"],
"234qzzjdzs5ocoj6o4ihzorq":["oncescomidas","fer 🥀💌"],
"ep5lrshitpsjuwd4oqfrqvfz":"onceoutofnature",
"xdq6jlbvahu2y4rmy2cfjvif":["onceri","Onceri"],
"x34xe3cc5hqkxzl3dbg5dkyd":["oncerepublican","Oncerepublican (Ex-X)"],
"y6dic4o2efqrd7ottut7iksd":["onceuponenglish","Rick"],
"w27r3jpgubgovdkd3g7ogecp":["onedrive","Drive once"],
"wtkiwexfxjlrn6bus5dvxnhk":["oncelostgames","Once Lost Games"],
"3ztynpsjzt2j3q37ovtiolze":["onceuponanother","Pon"],
"7dpdnvdkyh2wsshlry4boftm":"oncetwicebrice",
"qkdq6k4vweberredw3d6lriw":"oncadus",
"6wd72mtuwodwvytgzg7esabu":"onclevader",
"4nmkbnu4adwdxi3mrgszjw5j":["openget","bass once again"],
"ugmxjyccuvxdznx2bulkyuqm":["paulmeonce","Paul Me Once"],
"l6zjqwlvgwp4p5hxm2zm44um":["rip1ag","11 y once"],
"nykhe44evmloxxw6z4qmusf7":["robertsburton","Rob (s graves) Burton, once and future non-existent entity"],
"4n642klyvdcpx54kd6qlqai3":["seasonalbug","once called MarDiKrass on a platform once called twitter :p"],
"dlawukizh2wjvua4mijx5lso":["sheebamammen","InterestedInTooManyThingsAtOnce"],
"lxkzxwtzcihq7o6ivsdq4ilx":["skellulite","Skellulite || doing 27 sidequests at once"],
"yay7oawsffhew2ccljgtys7h":["snorristurluson","oncle Daniel"],
"pixzjv2uiimlm4aha5fcgfvo":["sugoishiba","The Once-ler of Bluesky"],
"s6rit7hwqccztfnx5miydae4":["syzonc","SyzOnc LLC"],
"me4ooueg4bebzqgfs5vzrpnj":["thejokesboy","the once and future jokesboy"],
"sdugvsu7yiqh5adq3rme4lle":["thereoncewasahorse","There once was a horse... "],
"nqqcwplceytbhw5vs7roznkc":["theblackprince","once & future king"],
"z3xjaefzmfu74pkju5wksmbl":["tigris-onca","Frion"],
"xv5kjmyx4jxz55hbkts7qwzl":["travisemajbers","Coochie Bugatti 69 (Travi/TraviOncé)"],
"nnljjnr7m34co3mm5qwcnyxm":["tyleroncesaid","Tyler Joseph Once Said 💀"],
"jjf46qfb3u77c3rnyo2xjh33":["unclejohnny","m’Oncle Johnny"],
"dnghlkykggyibqtha5qcokda":["unclegabbadoo","Oncle Gabbadoo"],
"sxz3rpgnbymukky3xwaswwga":["unnatural20","Unnatural20, the once and future Hobbit"],
"lkudk2ffdpwvco25izqs26l7":["useyourallusion","never fucked up once"],
"f3qbbjkcxwx77fi2c3vhw4yk":["wena1031","🎀 wena ♡ i was crazy once"],
"udawyrehma5ftpev6g66dget":["whygavs","ONCE AGAIN THE MAGIC OF SCIENCE PREVAILS! too much?"],
"fdoy3ilalt46fukorrhj37jk":["wingssomnia","Som🌻body once told me"]
}
