{
"pwbxp2ndlt6utgqdf5c7b2pz":["ofbooksandbikes","Rebecca Hussey"],
"cdvtxdi436u4w5aooqmei3ov":["ofbrokenwolves","Alice the Wolfe"],
"hzfopubiugc3zpwxfv2m7klk":"ofbagril",
"rbri3g5htfocqjlv3uwfti7p":["ofbeautyandrage15","Ash Ⴟ"],
"ffjeq47ydudd52w24j352upa":"ofboneandink",
"ndv22qzyxjyp5bxw7vtavnr7":"ofbooksandroyaltea",
"cj4sqhmwrhy5bvmdefi3qbsn":["ofbeautynrage","Red"],
"5yuul3iyz3uzsuqwewus7gov":["ofblacklanterns","Dylan Black Lanterns"],
"7sopsiozgwr4zfrekvsee6ac":["ofb","Oliver"],
"n33r6yue3a7tr4uwspnruypv":"ofbok",
"5jcgdzyhow5ol22uql7epvm7":"ofbricks",
"eui2hxkf2wba4nmlfmo2jyee":"ofbubblesandreams",
"am5fv4dis2fl3x4jgtu3f2rf":["ofbunaliyorum","OfBunalıyorum"],
"cj2r4iehzoqkbwwgbqdq72bf":["ofbladesntails","Of Blades & Tails"]
}
