{
"r5o6rqo3sjie7wsah3ycyoht":["astro4dev","IAU-OAD"],
"mkrodcctxuilvlivlby7m63v":["edsonjsl","Edson, o abençoado "],
"uoo22zcqejz7mkblgqlufeba":["oadegbola","Onyx"],
"6fi7cj46wl5zkjbhyys7xtua":"oadalbertoneto",
"rply2o6ht3foxdrvt72nets6":["oadancardoso","paul nescau"],
"f2sumbi44avuv3d3ogq23hry":["oadilsonrocha","Adilson Rocha Ferreira"],
"vv7jjrbkwksavc7sosqursnq":"oadugen",
"layc5dtjnuurho2q2utyy2e7":["oadnama","a"],
"6jhml5jkgpmi7vypmph5am23":["oadsoy","Orcun Adsoy"],
"qncqq7ikvzzumbbjis3gwj5g":["oadbek","Oadbek"],
"wobz7ow3jyoj4vz4lywf553j":"oadayo",
"sjgq5q55px43zsy4dngmmsh4":"oadoletskaya",
"g33ahaoghqs5l7jtbknleazh":["oadelino","mending"],
"s4xat4szz4f5dv56b2xe2ibu":["therealoadara","Oadara🕊️"]
}
